{"cameraMode":{"drawMode":0,"name":"Shaded","section":"Shading Mode"},"sceneLighting":true,"audioPlay":false,"sceneViewState":{"showFog":true,"showMaterialUpdate":false,"showSkybox":true,"showFlares":true,"showImageEffects":true,"showParticleSystems":true},"in2DMode":false,"pivot":{"x":352.7383728027344,"y":-205.4862060546875,"z":23.390045166015626},"rotation":{"x":-0.20109476149082185,"y":-0.6414552927017212,"z":0.17960146069526673,"w":-0.7182196378707886},"size":513.62060546875,"orthographic":false}